pydmsp/__init__.py
pydmsp/_dmspexeptions.py
pydmsp/_fromgz.py
pydmsp/_makedataset.py
pydmsp/_tablesE.py
pydmsp/_tablesG.py
pydmsp/_transformdataset.py
pydmsp/j5f1607276
pydmsp/j5f1607276.gz
pydmsp/tests/__init__.py
pydmsp/tests/j4f0682362
pydmsp/tests/j4f0682362.gz
pydmsp/tests/j4f0784315.gz
pydmsp/tests/j4f0787122.gz
pydmsp/tests/j4f0787122old.gz
pydmsp/tests/j4f0787124.gz
pydmsp/tests/j4f0787138.gz
pydmsp/tests/j4f0893200
pydmsp/tests/j4f0893200.gz
pydmsp/tests/j4f1100099.gz
pydmsp/tests/j4f1202201.gz
pydmsp/tests/j4f1507276
pydmsp/tests/j4f1507276.gz
pydmsp/tests/j5f1607276
pydmsp/tests/j5f1607276.gz
pydmsp/tests/j5f1623255
pydmsp/tests/j5f1623255.gz
pydmsp/tests/test00.py
pydmsp/tests/test01.py
pydmsp/tests/testing/j4f0682362.gz
pydmsp/tests/testing/j4f0683195.gz
pydmsp/tests/testing/j4f0684262.gz
pydmsp/tests/testing/j4f0685277.gz
pydmsp/tests/testing/j4f0687092.gz
pydmsp/tests/testing/j4f0786270.gz
pydmsp/tests/testing/j4f0888005.gz
pydmsp/tests/testing/j4f0889041.gz
pydmsp/tests/testing/j4f0890228.gz
pydmsp/tests/testing/j4f0891115.gz
pydmsp/tests/testing/j4f0893200.gz
pydmsp/tests/testing/j4f0894171.gz
pydmsp/tests/testing/j4f1092311.gz
pydmsp/tests/testing/j4f1097071.gz
pydmsp/tests/testing/j4f1100005.gz
pydmsp/tests/testing/j4f1199145.gz
pydmsp/tests/testing/j4f1295157.gz
pydmsp/tests/testing/j4f1296338.gz
pydmsp/tests/testing/j4f1301287.gz
pydmsp/tests/testing/j4f1302201.gz
pydmsp/tests/testing/j4f1303252.gz
pydmsp/tests/testing/j4f1304062.gz
pydmsp/tests/testing/j4f1305352.gz
pydmsp/tests/testing/j4f1306085.gz
pydmsp/tests/testing/j4f1398254.gz
pydmsp/tests/testing/j4f1508320.gz
pydmsp/tests/testing/j5f1607276.gz
pydmsp/tests/testing/j5f1609241.gz
pydmsp/tests/testing/j5f1610166.gz
pydmsp/tests/testing/j5f1611249.gz
pydmsp/tests/testing/j5f1612235.gz
pydmsp/tests/testing/j5f1613306.gz
pydmsp/tests/testing/j5f1615193.gz
pydmsp/tests/testing/j5f1616327.gz
pydmsp/tests/testing/j5f1617165.gz
pydmsp/tests/testing/j5f1618262.gz
pydmsp-0.1.8.dist-info/METADATA
pydmsp-0.1.8.dist-info/WHEEL
pydmsp-0.1.8.dist-info/RECORD
