Metadata-Version: 2.1
Name: pydmsp
Version: 0.1.8
Summary: DMSP converter
Author: ViktoriaGrishkina
Author-email: miheykoviktoria@yandex.ru
Requires-Python: >=3.9,<4.0
Classifier: Programming Language :: Python :: 3
Classifier: Programming Language :: Python :: 3.9
Classifier: Programming Language :: Python :: 3.10
Classifier: Programming Language :: Python :: 3.11
Classifier: Programming Language :: Python :: 3.12
